setup.py
Horton.egg-info/PKG-INFO
Horton.egg-info/SOURCES.txt
Horton.egg-info/dependency_links.txt
Horton.egg-info/requires.txt
Horton.egg-info/top_level.txt
horton/__init__.py
horton/conway.py
horton/grid.py
horton/render/__init__.py
horton/render/pg.py