Metadata-Version: 1.1
Name: Horton
Version: 0.1.1
Summary: 
